{
    "ppa 100 - Intro Public Policy+Admin - 3 Units": [
        {
            "days": "",
            "startTime": "",
            "endTime": ""
        }
    ],
    "ppa 200 - Intro Public Policy+Adm - 3 Units": [
        {
            "days": "T",
            "startTime": "0600PM",
            "endTime": "0850PM"
        },
        {
            "days": "W",
            "startTime": "0600PM",
            "endTime": "0850PM"
        }
    ],
    "ppa 205 - Research Publ Policy+Adm - 3 Units": [
        {
            "days": "M",
            "startTime": "0600PM",
            "endTime": "0850PM"
        },
        {
            "days": "W",
            "startTime": "0600PM",
            "endTime": "0850PM"
        }
    ],
    "ppa 220A - Applied Econ Analysis I - 3 Units": [
        {
            "days": "M",
            "startTime": "0600PM",
            "endTime": "0850PM"
        },
        {
            "days": "R",
            "startTime": "0600PM",
            "endTime": "0850PM"
        }
    ],
    "ppa 230 - Public Budgeting+Finance - 3 Units": [
        {
            "days": "T",
            "startTime": "0600PM",
            "endTime": "0850PM"
        },
        {
            "days": "R",
            "startTime": "0600PM",
            "endTime": "0830PM"
        }
    ],
    "ppa 240A - Public Mgmt+Admin I - 3 Units": [
        {
            "days": "T",
            "startTime": "0600PM",
            "endTime": "0850PM"
        },
        {
            "days": "W",
            "startTime": "0600PM",
            "endTime": "0850PM"
        }
    ],
    "ppa 270 - Collaborative Policy - 3 Units": [
        {
            "days": "T",
            "startTime": "0600PM",
            "endTime": "0850PM"
        }
    ],
    "ppa 500 - Culminating Experience - 3 Units": [
        {
            "days": "",
            "startTime": "",
            "endTime": ""
        }
    ]
}