{
    "thea 1 - Introduction To Theatre - 3 Units": [
        {
            "days": "MW",
            "startTime": "1200PM",
            "endTime": "0115PM"
        }
    ],
    "thea 2 - Hist-Ancient To Renaissan - 3 Units": [
        {
            "days": "MWF",
            "startTime": "1000AM",
            "endTime": "1050AM"
        }
    ],
    "thea 5 - Aesthetics Theatre+Film - 3 Units": [
        {
            "days": "MW",
            "startTime": "0300PM",
            "endTime": "0440PM"
        }
    ],
    "thea 9 - Appreciation Of Acting - 3 Units": [
        {
            "days": "TR",
            "startTime": "0900AM",
            "endTime": "1015AM"
        },
        {
            "days": "MW",
            "startTime": "0130PM",
            "endTime": "0245PM"
        },
        {
            "days": "TR",
            "startTime": "0130PM",
            "endTime": "0245PM"
        },
        {
            "days": "",
            "startTime": "",
            "endTime": ""
        }
    ],
    "thea 11 - Acting Study I - 3 Units": [
        {
            "days": "MW",
            "startTime": "1200PM",
            "endTime": "0140PM"
        }
    ],
    "thea 14 - Stage Makeup/Costume Construct - 3 Units": [
        {
            "days": "T",
            "startTime": "0900AM",
            "endTime": "1040AM"
        },
        {
            "days": "R",
            "startTime": "0900AM",
            "endTime": "1040AM"
        }
    ],
    "thea 16 - Stagecraft - 3 Units": [
        {
            "days": "M",
            "startTime": "1200PM",
            "endTime": "0140PM"
        },
        {
            "days": "W",
            "startTime": "1200PM",
            "endTime": "0140PM"
        }
    ],
    "thea 20 - Lighting - 3 Units": [
        {
            "days": "T",
            "startTime": "1200PM",
            "endTime": "0140PM"
        },
        {
            "days": "R",
            "startTime": "1200PM",
            "endTime": "0140PM"
        }
    ],
    "thea 21 - First Year Seminar - 3 Units": [
        {
            "days": "TR",
            "startTime": "1030AM",
            "endTime": "1145AM"
        }
    ],
    "thea 102A - Voice+Movement I - 3 Units": [
        {
            "days": "TR",
            "startTime": "0900AM",
            "endTime": "1040AM"
        }
    ],
    "thea 104 - Acting Study II - 3 Units": [
        {
            "days": "TR",
            "startTime": "0300PM",
            "endTime": "0440PM"
        }
    ],
    "thea 107 - Directing - 3 Units": [
        {
            "days": "TR",
            "startTime": "0300PM",
            "endTime": "0450PM"
        }
    ],
    "thea 115A - Multicultural Puppetry - 3 Units": [
        {
            "days": "M",
            "startTime": "0500PM",
            "endTime": "0550PM"
        },
        {
            "days": "M",
            "startTime": "0600PM",
            "endTime": "0800PM"
        }
    ],
    "thea 118 - Children's Theatre - 3 Units": [
        {
            "days": "MW",
            "startTime": "0300PM",
            "endTime": "0415PM"
        },
        {
            "days": "TR",
            "startTime": "0300PM",
            "endTime": "0415PM"
        }
    ],
    "thea 120A - Practicum Technical Production - 1 Units": [
        {
            "days": "T",
            "startTime": "0600PM",
            "endTime": "0850PM"
        },
        {
            "days": "R",
            "startTime": "0600PM",
            "endTime": "0850PM"
        },
        {
            "days": "",
            "startTime": "",
            "endTime": ""
        }
    ],
    "thea 120B - Practicum Technical Production - 2 Units": [
        {
            "days": "W",
            "startTime": "0600PM",
            "endTime": "0850PM"
        }
    ],
    "thea 121 - Rehearsal & Performance - 1 Units": [
        {
            "days": "M",
            "startTime": "0300PM",
            "endTime": "0550PM"
        },
        {
            "days": "M",
            "startTime": "0600PM",
            "endTime": "0850PM"
        },
        {
            "days": "MW",
            "startTime": "0300PM",
            "endTime": "0440PM"
        }
    ],
    "thea 123 - Lighting and Set Design - 3 Units": [
        {
            "days": "M",
            "startTime": "0900AM",
            "endTime": "1040AM"
        },
        {
            "days": "W",
            "startTime": "0900AM",
            "endTime": "1040AM"
        }
    ],
    "thea 155 - Contemporary World Cinema - 3 Units": [
        {
            "days": "W",
            "startTime": "0530PM",
            "endTime": "0830PM"
        }
    ],
    "thea 170 - Afro-American Thea/Culture - 3 Units": [
        {
            "days": "TR",
            "startTime": "0900AM",
            "endTime": "1015AM"
        }
    ],
    "thea 173 - Cntmp Chicano/Latino Thea - 3 Units": [
        {
            "days": "MW",
            "startTime": "1200PM",
            "endTime": "0115PM"
        }
    ],
    "thea 174 - Multicul Persp Am Theatre - 3 Units": [
        {
            "days": "TR",
            "startTime": "1030AM",
            "endTime": "1145AM"
        }
    ],
    "thea 175 - Multicul Persp Am Film - 3 Units": [
        {
            "days": "T",
            "startTime": "0530PM",
            "endTime": "0820PM"
        }
    ],
    "thea 199 - Special Problems Theatre - 3 Units": [
        {
            "days": "",
            "startTime": "",
            "endTime": ""
        }
    ]
}